{
 "year": "2016",
 "week": "16",
 "sortKey": "2016-16",
 "items": [
  {
   "item_id": "1263338403",
   "given_url": "https://drive.google.com/file/d/0B88lYzphdgSlX0JmN1ktU1JINU0/edit?pageId=107507099462922217354",
   "given_title": "There Is No Ghost In The Shell.mp4 - Google Drive",
   "resolved_title": "There Is No Ghost In The Shell.mp4 - Google Drive",
   "resolved_url": "https://drive.google.com/file/d/0B88lYzphdgSlX0JmN1ktU1JINU0/edit?pageId=107507099462922217354",
   "time_updated": "2016-04-20T17:57:22+01:00",
   "time_added": "2016-04-20T17:57:22+01:00"
  },
  {
   "item_id": "11219607",
   "given_url": "http://www.vtc.com/products/Design-Patterns-tutorials.htm",
   "given_title": "Design Patterns",
   "resolved_title": "Design Patterns Course",
   "resolved_url": "https://www.vtc.com/products/Design-Patterns-tutorials.htm",
   "time_updated": "2016-04-21T16:46:38+01:00",
   "time_added": "2016-04-21T16:45:39+01:00"
  },
  {
   "item_id": "1263314179",
   "given_url": "http://www.factmag.com/2016/04/20/best-post-rock-albums/",
   "given_title": "The 30 best post-rock albums of all time",
   "resolved_title": "The 30 best post-rock albums of all time",
   "resolved_url": "https://www.factmag.com/2016/04/20/best-post-rock-albums/",
   "time_updated": "2016-04-21T16:52:12+01:00",
   "time_added": "2016-04-21T16:52:03+01:00"
  },
  {
   "item_id": "19540142",
   "given_url": "http://dimecasts.net/Casts/ByTag/Design%20Patterns",
   "given_title": "DimeCasts.Net Episodes for Design Patterns (11)",
   "resolved_title": "Design Patterns Episodes",
   "resolved_url": "http://dimecasts.net/Casts/ByTag/Design%20Patterns",
   "time_updated": "2016-04-21T16:45:35+01:00",
   "time_added": "2016-04-21T16:45:35+01:00"
  },
  {
   "item_id": "1263830285",
   "given_url": "http://www.stereogum.com/1872593/pj-harvey-albums-from-worst-to-best/",
   "given_title": "PJ Harvey Albums From Worst To Best - Stereogum",
   "resolved_title": "PJ Harvey Albums From Worst To Best",
   "resolved_url": "http://www.stereogum.com/1872593/pj-harvey-albums-from-worst-to-best/",
   "time_updated": "2016-04-21T16:52:26+01:00",
   "time_added": "2016-04-21T05:35:52+01:00"
  },
  {
   "item_id": "1254949422",
   "given_url": "http://www.lrb.co.uk/v38/n08/perry-anderson/crisis-in-brazil",
   "given_title": "Perry Anderson · Crisis in Brazil · LRB 21 April 2016",
   "resolved_title": "Crisis in Brazil",
   "resolved_url": "https://www.lrb.co.uk/v38/n08/perry-anderson/crisis-in-brazil",
   "time_updated": "2016-04-18T21:01:51+01:00",
   "time_added": "2016-04-18T21:01:51+01:00"
  }
 ]
}