{
 "year": "2022",
 "week": "24",
 "sortKey": "2022-24",
 "items": [
  {
   "item_id": "3636577821",
   "given_url": "https://nolanlawson.com/2022/06/09/the-collapse-of-complex-software/",
   "given_title": "The collapse of complex software | Read the Tea Leaves",
   "resolved_title": "The collapse of complex software",
   "resolved_url": "https://nolanlawson.com/2022/06/09/the-collapse-of-complex-software/",
   "time_updated": "2022-06-18T15:17:31Z",
   "time_added": "2022-06-09T19:25:55Z"
  },
  {
   "item_id": "3623017185",
   "given_url": "https://developer.chrome.com/blog/paint-holding/",
   "given_title": "Paint Holding - reducing the flash of white on same-origin navigations - Ch",
   "resolved_title": "Paint Holding - reducing the flash of white on same-origin navigations",
   "resolved_url": "https://developer.chrome.com/blog/paint-holding/",
   "time_updated": "2022-06-18T15:17:31Z",
   "time_added": "2022-06-09T21:51:05Z"
  },
  {
   "item_id": "3636759312",
   "given_url": "https://www.uol.com.br/vivabem/noticias/redacao/2022/06/09/intercambio-mudanca-de-pais-como-imigrar-sem-prejudicar-o-emocional.htm",
   "given_title": "Intercâmbio, mudança de país: como cuidar do emocional ao ir morar fora? - ",
   "resolved_title": "Intercâmbio, mudança de país: como imigrar sem prejudicar o emocional?",
   "resolved_url": "https://www.uol.com.br/vivabem/noticias/redacao/2022/06/09/intercambio-mudanca-de-pais-como-imigrar-sem-prejudicar-o-emocional.htm",
   "time_updated": "2022-06-18T15:17:31Z",
   "time_added": "2022-06-09T22:37:24Z"
  },
  {
   "item_id": "3632340496",
   "given_url": "https://paperform.co/blog/toxic-productivity/",
   "given_title": "Are You Suffering from Toxic Productivity?",
   "resolved_title": "Are You Suffering from Toxic Productivity?",
   "resolved_url": "https://paperform.co/blog/toxic-productivity/",
   "time_updated": "2022-06-18T15:17:31Z",
   "time_added": "2022-06-10T12:04:01Z"
  },
  {
   "item_id": "3631670382",
   "given_url": "https://eng.uber.com/data-race-patterns-in-go/",
   "given_title": "Data Race Patterns in Go",
   "resolved_title": "Data Race Patterns in Go",
   "resolved_url": "https://eng.uber.com/data-race-patterns-in-go/",
   "time_updated": "2022-06-18T15:17:31Z",
   "time_added": "2022-06-10T23:28:10Z"
  },
  {
   "item_id": "431602092",
   "given_url": "https://en.m.wikipedia.org/wiki/Ishikawa_Goemon",
   "given_title": "Ishikawa Goemon - Wikipedia",
   "resolved_title": "Ishikawa Goemon",
   "resolved_url": "https://en.wikipedia.org/wiki/Ishikawa_Goemon",
   "time_updated": "2022-06-18T15:17:31Z",
   "time_added": "2022-06-11T01:00:41Z"
  },
  {
   "item_id": "3638687696",
   "given_url": "https://www.uol.com.br/esporte/reportagens-especiais/na-3-divisao-argel-quer-abrir-portas-aos-treinadores-brasileiros-em-portugal/#page8",
   "given_title": "Argel quer abrir as portas para os treinadores brasileiros em Portugal",
   "resolved_title": "Na contramão da nova ordem",
   "resolved_url": "https://www.uol.com.br/esporte/reportagens-especiais/na-3-divisao-argel-quer-abrir-portas-aos-treinadores-brasileiros-em-portugal/",
   "time_updated": "2022-06-18T15:17:32Z",
   "time_added": "2022-06-12T11:41:21Z"
  },
  {
   "item_id": "3638687697",
   "given_url": "https://mobile.twitter.com/DeannaHoak/status/970129313415749632?ref_src=twsrc%5Etfw%7Ctwcamp%5Etweetembed%7Ctwterm%5E970362597265391616%7Ctwgr%5E%7Ctwcon%5Es3_\u0026ref_url=https%3A%2F%2Fmetro.co.uk%2F2018%2F03%2F07%2Fmillennials-created-language-7368643%2F",
   "given_title": "Deanna Hoak no Twitter: \"My master’s was in sociolinguistics, and I absolut",
   "resolved_title": "Deanna Hoak",
   "resolved_url": "https://mobile.twitter.com/deannahoak/status/970129313415749632",
   "time_updated": "2022-06-18T15:17:32Z",
   "time_added": "2022-06-12T15:49:55Z"
  },
  {
   "item_id": "3638172341",
   "given_url": "https://cajundiscordian.medium.com/what-is-lamda-and-what-does-it-want-688632134489",
   "given_title": "What is LaMDA and What Does it Want? | by Blake Lemoine | Jun, 2022 | Mediu",
   "resolved_title": "What is LaMDA and What Does it Want?",
   "resolved_url": "https://cajundiscordian.medium.com/what-is-lamda-and-what-does-it-want-688632134489",
   "time_updated": "2022-06-18T15:17:32Z",
   "time_added": "2022-06-12T17:38:42Z"
  },
  {
   "item_id": "3638587747",
   "given_url": "https://kk.org/thetechnium/what-everyone-knows/",
   "given_title": "The Technium: What Everyone Knows",
   "resolved_title": "What Everyone Knows",
   "resolved_url": "https://kk.org/thetechnium/what-everyone-knows/",
   "time_updated": "2022-06-18T15:17:32Z",
   "time_added": "2022-06-12T19:58:43Z"
  },
  {
   "item_id": "3639789995",
   "given_url": "https://dailyedit.com/blog/why-rust-is-a-great-choice-for-startups/",
   "given_title": "Why Rust is a great choice for startups – The Daily Edit",
   "resolved_title": "Why Rust is a great choice for startups",
   "resolved_url": "https://dailyedit.com/blog/why-rust-is-a-great-choice-for-startups/",
   "time_updated": "2022-06-14T15:23:05Z",
   "time_added": "2022-06-14T15:23:05Z"
  },
  {
   "item_id": "3640569588",
   "given_url": "https://tab.uol.com.br/noticias/redacao/2022/06/15/r-500-a-mais-garotos-de-programa-se-drogam-para-agradar-clientes-ricos.htm",
   "given_title": "'R$ 500 a mais': garotos de programa se drogam para agradar clientes ricos ",
   "resolved_title": "'R$ 500 a mais': garotos de programa se drogam para agradar clientes ricos",
   "resolved_url": "https://tab.uol.com.br/noticias/redacao/2022/06/15/r-500-a-mais-garotos-de-programa-se-drogam-para-agradar-clientes-ricos.htm",
   "time_updated": "2022-06-18T15:17:32Z",
   "time_added": "2022-06-15T11:50:03Z"
  },
  {
   "item_id": "3639762929",
   "given_url": "https://www.economist.com/culture/2022/06/14/mundane-chores-are-all-the-rage-in-gaming",
   "given_title": "Mundane chores are all the rage in gaming | The Economist",
   "resolved_title": "Mundane chores are all the rage in gaming",
   "resolved_url": "https://www.economist.com/culture/2022/06/14/mundane-chores-are-all-the-rage-in-gaming",
   "time_updated": "2022-06-18T15:17:32Z",
   "time_added": "2022-06-15T11:57:46Z"
  },
  {
   "item_id": "3640320561",
   "given_url": "https://twitter.com/swyx/status/1536832603411451905",
   "given_title": "swyx no Twitter: \"Every so often I love to be reminded of the biggest devto",
   "resolved_title": "swyx",
   "resolved_url": "https://twitter.com/swyx/status/1536832603411451905",
   "time_updated": "2022-06-15T14:12:44Z",
   "time_added": "2022-06-15T14:12:44Z"
  },
  {
   "item_id": "3640799354",
   "given_url": "https://twitter.com/jespow/status/1536978826344792064",
   "given_title": "Jesse Powell no Twitter: \"5/ What are they upset about? * DEI (Silicon Vall",
   "resolved_title": "Jesse Powell",
   "resolved_url": "https://twitter.com/jespow/status/1536978826344792064",
   "time_updated": "2022-06-15T19:12:35Z",
   "time_added": "2022-06-15T19:12:34Z"
  },
  {
   "item_id": "3640759184",
   "given_url": "https://www.nytimes.com/2022/06/15/technology/kraken-crypto-culture.html",
   "given_title": "Inside a Corporate Culture War Stoked by a Crypto C.E.O. - The New York Tim",
   "resolved_title": "Inside a Corporate Culture War Stoked by a Crypto C.E.O.",
   "resolved_url": "https://www.nytimes.com/2022/06/15/technology/kraken-crypto-culture.html",
   "time_updated": "2022-06-15T19:15:58Z",
   "time_added": "2022-06-15T19:15:58Z"
  },
  {
   "item_id": "3639055776",
   "given_url": "https://www.theatlantic.com/magazine/archive/2022/07/light-noise-pollution-animal-sensory-impact/638446/",
   "given_title": "How Light and Noise Pollution Confound Animals’ Senses - The Atlantic",
   "resolved_title": "How Animals Perceive the World",
   "resolved_url": "https://www.theatlantic.com/magazine/archive/2022/07/light-noise-pollution-animal-sensory-impact/638446/",
   "time_updated": "2022-06-18T15:17:32Z",
   "time_added": "2022-06-16T11:55:23Z"
  },
  {
   "item_id": "1989357930",
   "given_url": "https://rafaelfalcon.com.br/artigos/um-livro-para-ler-e-entender/",
   "given_title": "Um livro para ler — e entender – Rafael Falcón",
   "resolved_title": "Um livro para ler — e entender",
   "resolved_url": "https://rafaelfalcon.com.br/artigos/um-livro-para-ler-e-entender/",
   "time_updated": "2022-06-18T15:17:32Z",
   "time_added": "2022-06-16T18:04:21Z"
  },
  {
   "item_id": "3641250210",
   "given_url": "https://www.uol.com.br/vivabem/noticias/redacao/2022/06/16/congelar-bichinho-de-pelucia-funciona-veja-cuidados-para-evitar-a-rinite.htm",
   "given_title": "Congelar bicho de pelúcia? Veja cuidados para evitar rinite",
   "resolved_title": "Congelar pelúcia e mais 7 dicas fáceis para você combater a rinite alérgica",
   "resolved_url": "https://www.uol.com.br/vivabem/noticias/redacao/2022/06/16/congelar-bichinho-de-pelucia-funciona-veja-cuidados-para-evitar-a-rinite.htm",
   "time_updated": "2022-06-18T15:17:33Z",
   "time_added": "2022-06-16T18:15:12Z"
  },
  {
   "item_id": "3642696070",
   "given_url": "https://www.thelocal.se/20220614/swedophiles-the-foreigners-who-move-to-sweden-based-on-statistics-alone/?utm_source=dlvr.it\u0026utm_medium=facebook",
   "given_title": "Swedophiles: The foreigners who move to Sweden based on statistics alone",
   "resolved_title": "",
   "resolved_url": "https://www.thelocal.se/20220614/swedophiles-the-foreigners-who-move-to-sweden-based-on-statistics-alone/?utm_source=dlvr.it\u0026utm_medium=facebook",
   "time_updated": "2022-06-18T15:17:35Z",
   "time_added": "2022-06-16T18:15:34Z"
  },
  {
   "item_id": "3642167495",
   "given_url": "https://www.uol.com.br/esporte/reportagens-especiais/libertadores-rivais-explicam-o-que-o-sao-paulo-de-1992-tinha-de-diferente/#page4",
   "given_title": "São Paulo campeão da Libertadores 1992 estava à frente de seu tempo",
   "resolved_title": "À frente de seu tempo",
   "resolved_url": "https://www.uol.com.br/esporte/reportagens-especiais/libertadores-rivais-explicam-o-que-o-sao-paulo-de-1992-tinha-de-diferente/",
   "time_updated": "2022-06-18T15:17:33Z",
   "time_added": "2022-06-17T19:43:14Z"
  },
  {
   "item_id": "3642270082",
   "given_url": "https://noticias.uol.com.br/colunas/reinaldo-azevedo/2022/06/17/bruno-e-dom-por-que-pf-descartar-mandantes-e-aberracao-tecnica-e-politica.htm",
   "given_title": "Bruno e Dom: Por que PF descartar mandantes é aberração técnica e política ",
   "resolved_title": "Reinaldo Azevedo",
   "resolved_url": "https://noticias.uol.com.br/colunas/reinaldo-azevedo/2022/06/17/bruno-e-dom-por-que-pf-descartar-mandantes-e-aberracao-tecnica-e-politica.htm",
   "time_updated": "2022-06-18T15:17:33Z",
   "time_added": "2022-06-18T00:34:22Z"
  },
  {
   "item_id": "3642696073",
   "given_url": "https://mobile.twitter.com/swyx/status/1361279902889086980?s=20\u0026t=AWGEYKDwkBTy9eyjJZra5Q",
   "given_title": "swyx no Twitter: \"One thing I've consistently had to relearn in developer m",
   "resolved_title": "shawn swyx wang",
   "resolved_url": "https://mobile.twitter.com/swyx/status/1361279902889086980",
   "time_updated": "2022-06-18T15:17:35Z",
   "time_added": "2022-06-18T06:12:11Z"
  },
  {
   "item_id": "3639401273",
   "given_url": "https://www.andy.works/words/the-most-satisfying-checkbox",
   "given_title": "The World's Most Satisfying Checkbox | (Not Boring) Software",
   "resolved_title": "The World's Most Satisfying Checkbox",
   "resolved_url": "https://www.andy.works/words/the-most-satisfying-checkbox",
   "time_updated": "2022-06-18T15:17:26Z",
   "time_added": "2022-06-18T15:17:26Z"
  },
  {
   "item_id": "3290795866",
   "given_url": "https://www.stereogum.com/1793955/how-brian-wilson-helped-spawn-punk/columns/sounding-board/",
   "given_title": "How Brian Wilson Helped Spawn Punk",
   "resolved_title": "How Brian Wilson Helped Spawn Punk",
   "resolved_url": "https://www.stereogum.com/1793955/how-brian-wilson-helped-spawn-punk/columns/sounding-board/",
   "time_updated": "2022-06-23T23:00:37Z",
   "time_added": "2022-06-19T22:01:52Z"
  }
 ]
}