{
 "year": "2022",
 "week": "36",
 "sortKey": "2022-36",
 "items": [
  {
   "item_id": "3696187212",
   "given_url": "https://twitter.com/hillelogram/status/1562857436695760896",
   "given_title": "Hillel no Twitter: \"In \"Commonsense Computing\", Lewandowski et al argue tha",
   "resolved_title": "Hillel",
   "resolved_url": "https://twitter.com/hillelogram/status/1562857436695760896",
   "time_updated": "2022-09-05T01:38:33+01:00",
   "time_added": "2022-09-05T01:38:32+01:00"
  },
  {
   "item_id": "3695642893",
   "given_url": "https://www.thetechoutlook.com/news/current-affairs/peter-eckersley-the-founder-of-lets-encrypt-has-left-the-tech-industry-in-tears/amp/",
   "given_title": "Peter Eckersley, the founder of Let's Encrypt has left the tech industry in",
   "resolved_title": "Peter Eckersley, the founder of Let’s Encrypt has left the tech industry in tears",
   "resolved_url": "https://www.thetechoutlook.com/news/current-affairs/peter-eckersley-the-founder-of-lets-encrypt-has-left-the-tech-industry-in-tears/amp/",
   "time_updated": "2022-09-05T01:45:18+01:00",
   "time_added": "2022-09-05T01:45:17+01:00"
  },
  {
   "item_id": "3694729107",
   "given_url": "https://bam.kalzumeus.com/archive/optimal-amount-of-fraud/",
   "given_title": "The optimal amount of fraud is non-zero",
   "resolved_title": "The optimal amount of fraud is non-zero",
   "resolved_url": "https://bam.kalzumeus.com/archive/optimal-amount-of-fraud/",
   "time_updated": "2022-09-05T02:30:28+01:00",
   "time_added": "2022-09-05T02:30:27+01:00"
  },
  {
   "item_id": "3696561364",
   "given_url": "https://www1.folha.uol.com.br/blogs/sylvia-colombo/2022/09/cinco-chaves-para-entender-porque-chilenos-rejeitaram-constituicao.shtml",
   "given_title": "Cinco chaves para entender por que chilenos rejeitaram Constituição - 05/09",
   "resolved_title": "Cinco chaves para entender por que chilenos rejeitaram Constituição",
   "resolved_url": "https://www1.folha.uol.com.br/blogs/sylvia-colombo/2022/09/cinco-chaves-para-entender-porque-chilenos-rejeitaram-constituicao.shtml",
   "time_updated": "2022-09-05T21:56:01+01:00",
   "time_added": "2022-09-05T21:56:01+01:00"
  },
  {
   "item_id": "3696829504",
   "given_url": "https://www.nocloudflare.com/",
   "given_title": "Say No to Cloudflare",
   "resolved_title": "Say No to Cloudflare",
   "resolved_url": "https://www.nocloudflare.com/",
   "time_updated": "2022-09-06T12:57:33+01:00",
   "time_added": "2022-09-06T12:57:33+01:00"
  },
  {
   "item_id": "3697329929",
   "given_url": "https://mobile.twitter.com/ExplainedQuotes/status/1567114578731089921",
   "given_title": "Sakura Neko Sensei no Twitter: \"Have you ever wondered what it’s like to be",
   "resolved_title": "Sakura Neko Sensei",
   "resolved_url": "https://mobile.twitter.com/explainedquotes/status/1567114578731089921",
   "time_updated": "2022-09-06T16:55:14+01:00",
   "time_added": "2022-09-06T16:55:13+01:00"
  },
  {
   "item_id": "3697450833",
   "given_url": "https://twitter.com/hillelogram/status/1567193133833719808",
   "given_title": "Hillel no Twitter: \"Also half days\" / Twitter",
   "resolved_title": "Hillel",
   "resolved_url": "https://twitter.com/hillelogram/status/1567193133833719808",
   "time_updated": "2022-09-06T20:41:17+01:00",
   "time_added": "2022-09-06T20:41:16+01:00"
  },
  {
   "item_id": "3300708606",
   "given_url": "https://jacobian.org/2021/apr/7/embrace-the-grind/",
   "given_title": "Embrace the Grind - Jacob Kaplan-Moss",
   "resolved_title": "Embrace the Grind",
   "resolved_url": "https://jacobian.org/2021/apr/7/embrace-the-grind/",
   "time_updated": "2022-09-07T14:19:26+01:00",
   "time_added": "2022-09-07T14:19:26+01:00"
  },
  {
   "item_id": "3697976201",
   "given_url": "https://twitter.com/housecor/status/1567502647732625410",
   "given_title": "Cory House no Twitter: \"I ❤️ React. But, it’s not perfect. There are featur",
   "resolved_title": "Cory House",
   "resolved_url": "https://twitter.com/housecor/status/1567502647732625410",
   "time_updated": "2022-09-07T16:14:12+01:00",
   "time_added": "2022-09-07T16:14:12+01:00"
  },
  {
   "item_id": "3698152999",
   "given_url": "https://twitter.com/MMahlberg/status/1567510111463120897",
   "given_title": "Michael Mahlberg no Twitter: \"Great example for evolutionary design by @Jos",
   "resolved_title": "Michael Mahlberg",
   "resolved_url": "https://twitter.com/mmahlberg/status/1567510111463120897",
   "time_updated": "2022-09-07T20:08:27+01:00",
   "time_added": "2022-09-07T20:08:26+01:00"
  },
  {
   "item_id": "3698228721",
   "given_url": "https://twitter.com/hillelogram/status/1567606964397432832",
   "given_title": "Hillel no Twitter: \"\"Why would anybody use vim or emacs when there are mode",
   "resolved_title": "Hillel",
   "resolved_url": "https://twitter.com/hillelogram/status/1567606964397432832",
   "time_updated": "2022-09-07T22:38:33+01:00",
   "time_added": "2022-09-07T22:38:33+01:00"
  },
  {
   "item_id": "3697547355",
   "given_url": "https://twitter.com/SergioRocks/status/1567136823738044421",
   "given_title": "Sergio Pereira ? no Twitter: \"I've worked from home for 6 years now. During",
   "resolved_title": "Sergio Pereira 🚀",
   "resolved_url": "https://twitter.com/sergiorocks/status/1567136823738044421",
   "time_updated": "2022-09-07T23:00:50+01:00",
   "time_added": "2022-09-07T23:00:50+01:00"
  },
  {
   "item_id": "605825994",
   "given_url": "https://spaceplace.nasa.gov/barycenter/en/",
   "given_title": "What Is a Barycenter? | NASA Space Place – NASA Science for Kids",
   "resolved_title": "What Is a Barycenter?",
   "resolved_url": "http://spaceplace.nasa.gov/barycenter/en/",
   "time_updated": "2022-09-08T03:23:36+01:00",
   "time_added": "2022-09-08T03:23:34+01:00"
  },
  {
   "item_id": "3698640498",
   "given_url": "https://m.youtube.com/watch?t=94\u0026v=hl9ebEK5zrs\u0026feature=youtu.be",
   "given_title": "The Pervert's Guide to Cinema 2006 excerpts on Dr Strangelove and Eyes Wide",
   "resolved_title": "The Pervert's Guide to Cinema 2006 excerpts on Dr Strangelove and Eyes Wide Shut",
   "resolved_url": "https://www.youtube.com/watch?v=hl9ebEK5zrs",
   "time_updated": "2022-09-08T13:16:25+01:00",
   "time_added": "2022-09-08T13:16:22+01:00"
  },
  {
   "item_id": "3698089033",
   "given_url": "https://istio.io/latest/blog/2022/introducing-ambient-mesh/",
   "given_title": "Istio / Introducing Ambient Mesh",
   "resolved_title": "Introducing Ambient Mesh",
   "resolved_url": "https://istio.io/latest/blog/2022/introducing-ambient-mesh/",
   "time_updated": "2022-09-08T14:40:12+01:00",
   "time_added": "2022-09-08T14:40:12+01:00"
  },
  {
   "item_id": "3121669365",
   "given_url": "http://liamrosen.com/arguments.html",
   "given_title": "Beginner's Guide to Arguing Constructively",
   "resolved_title": "Beginner's Guide to Arguing Constructively",
   "resolved_url": "http://liamrosen.com/arguments.html",
   "time_updated": "2022-09-08T15:21:41+01:00",
   "time_added": "2022-09-08T15:21:41+01:00"
  },
  {
   "item_id": "2706497431",
   "given_url": "https://thevaluable.dev/guide-debate-software-developer-skill/",
   "given_title": "A Guide for Debating Effectively as a Software Developers",
   "resolved_title": "A Guide for Debating Effectively as a Software Developers",
   "resolved_url": "https://thevaluable.dev/guide-debate-software-developer-skill/",
   "time_updated": "2022-09-08T15:21:46+01:00",
   "time_added": "2022-09-08T15:21:46+01:00"
  },
  {
   "item_id": "3698830128",
   "given_url": "https://twitter.com/copyconstruct/status/1567921940798783499",
   "given_title": "Cindy Sridharan no Twitter: \"Technical writing should be a required trainin",
   "resolved_title": "Cindy Sridharan",
   "resolved_url": "https://twitter.com/copyconstruct/status/1567921940798783499",
   "time_updated": "2022-09-08T18:37:30+01:00",
   "time_added": "2022-09-08T18:37:29+01:00"
  },
  {
   "item_id": "3699329786",
   "given_url": "https://mobile.twitter.com/andrestaltz/status/1568176915172704259",
   "given_title": "André Staltz no Twitter: \"Usability in software is about delivering: 1. Saf",
   "resolved_title": "André Staltz",
   "resolved_url": "https://mobile.twitter.com/andrestaltz/status/1568176915172704259",
   "time_updated": "2022-09-09T12:28:56+01:00",
   "time_added": "2022-09-09T12:28:54+01:00"
  },
  {
   "item_id": "3507149844",
   "given_url": "https://towardsdatascience.com/on-the-importance-of-bayesian-thinking-in-everyday-life-a74475fcceeb",
   "given_title": "Bayesian Thinking in Everyday Life | Towards Data Science",
   "resolved_title": "On the Importance of Bayesian Thinking in Everyday Life",
   "resolved_url": "https://towardsdatascience.com/on-the-importance-of-bayesian-thinking-in-everyday-life-a74475fcceeb",
   "time_updated": "2022-09-09T12:44:05+01:00",
   "time_added": "2022-09-09T12:44:04+01:00"
  },
  {
   "item_id": "3532099063",
   "given_url": "https://blog.horner.tj/how-to-kinda-download-more-ram/",
   "given_title": "How to (Kinda) Download More RAM",
   "resolved_title": "How to (Kinda) Download More RAM",
   "resolved_url": "https://blog.horner.tj/how-to-kinda-download-more-ram/",
   "time_updated": "2022-09-09T13:26:34+01:00",
   "time_added": "2022-09-09T13:26:34+01:00"
  },
  {
   "item_id": "3699245668",
   "given_url": "https://teamplify.com/blog/why-public-chats-are-better-than-direct-messages/",
   "given_title": "Why public chats are better than direct messages - Teamplify blog",
   "resolved_title": "Why public chats are better than direct messages",
   "resolved_url": "https://teamplify.com/blog/why-public-chats-are-better-than-direct-messages/",
   "time_updated": "2022-09-09T14:35:12+01:00",
   "time_added": "2022-09-09T14:35:12+01:00"
  },
  {
   "item_id": "3699052534",
   "given_url": "https://twitter.com/eevee/status/1568006762481201154",
   "given_title": "eevee no Twitter: \"i think the most important part of mathematics is the id",
   "resolved_title": "eevee",
   "resolved_url": "https://twitter.com/eevee/status/1568006762481201154",
   "time_updated": "2022-09-09T20:43:59+01:00",
   "time_added": "2022-09-09T20:43:59+01:00"
  },
  {
   "item_id": "408209070",
   "given_url": "https://www.maa.org/external_archive/devlin/LockhartsLament.pdf",
   "given_title": "Microsoft Word - LockhartsLament.doc - LockhartsLament.pdf",
   "resolved_title": "",
   "resolved_url": "https://www.maa.org/external_archive/devlin/LockhartsLament.pdf",
   "time_updated": "2022-09-10T00:06:03+01:00",
   "time_added": "2022-09-10T00:06:03+01:00"
  },
  {
   "item_id": "3317294998",
   "given_url": "https://buttondown.email/hillelwayne/archive/why-uml-really-died/",
   "given_title": "Why UML \"Really\" Died • Buttondown",
   "resolved_title": "Why UML \"Really\" Died",
   "resolved_url": "https://buttondown.email/hillelwayne/archive/why-uml-really-died/",
   "time_updated": "2022-09-10T00:43:19+01:00",
   "time_added": "2022-09-10T00:43:18+01:00"
  },
  {
   "item_id": "347540856",
   "given_url": "https://en.wikipedia.org/wiki/A_Mathematician%27s_Lament",
   "given_title": "A Mathematician's Lament - Wikipedia",
   "resolved_title": "A Mathematician's Lament",
   "resolved_url": "https://en.wikipedia.org/wiki/A_Mathematician%27s_Lament",
   "time_updated": "2022-09-10T03:53:13+01:00",
   "time_added": "2022-09-10T03:53:13+01:00"
  },
  {
   "item_id": "3699996699",
   "given_url": "https://noticias.uol.com.br/newsletters/uol-daniela-pinheiro/2022/09/09/duas-cenas-do-bicentenario-e-do-brasil-em-lisboa.htm?utm_source=uol.com.br\u0026utm_medium=referral\u0026utm_campaign=daniela-pinheiro\u0026utm_content=ver-edicao",
   "given_title": "Daniela Pinheiro",
   "resolved_title": "UOL Newsletters",
   "resolved_url": "https://noticias.uol.com.br/newsletters/uol-daniela-pinheiro/2022/09/09/duas-cenas-do-bicentenario-e-do-brasil-em-lisboa.htm",
   "time_updated": "2022-09-10T13:06:44+01:00",
   "time_added": "2022-09-10T13:06:40+01:00"
  },
  {
   "item_id": "2693550160",
   "given_url": "https://acoup.blog/2019/08/16/collections-this-isnt-sparta-part-i-spartan-school/",
   "given_title": "Collections: This. Isn’t. Sparta. Part I: Spartan School – A Collection of ",
   "resolved_title": "Collections: This. Isn’t. Sparta. Part I: Spartan School",
   "resolved_url": "https://acoup.blog/2019/08/16/collections-this-isnt-sparta-part-i-spartan-school/",
   "time_updated": "2022-09-10T13:07:02+01:00",
   "time_added": "2022-09-10T13:07:04+01:00"
  },
  {
   "item_id": "3700085933",
   "given_url": "https://hanmadistory.wordpress.com/2016/05/30/stress/",
   "given_title": "Stress 스트레스 – hanmadi",
   "resolved_title": "Stress 스트레스",
   "resolved_url": "https://hanmadistory.wordpress.com/2016/05/30/stress/",
   "time_updated": "2022-09-10T16:06:55+01:00",
   "time_added": "2022-09-10T16:06:52+01:00"
  },
  {
   "item_id": "3700090363",
   "given_url": "https://mobile.twitter.com/allenholub/status/1568610716793413634",
   "given_title": "Allen Holub no Twitter: \"I get so sick to death of the \"customers don't kno",
   "resolved_title": "Allen Holub",
   "resolved_url": "https://mobile.twitter.com/allenholub/status/1568610716793413634",
   "time_updated": "2022-09-10T16:15:50+01:00",
   "time_added": "2022-09-10T16:15:49+01:00"
  },
  {
   "item_id": "3700182352",
   "given_url": "https://www.shiftrle.gg/articles/complexity-gaming-to-complete-cross-region-transfer-for-crr",
   "given_title": "Complexity To Complete Cross-Region Transfer For crr — Shift — Rocket Leagu",
   "resolved_title": "Complexity To Complete Cross-Region Transfer For crr",
   "resolved_url": "https://www.shiftrle.gg/articles/complexity-gaming-to-complete-cross-region-transfer-for-crr",
   "time_updated": "2022-09-10T19:29:41+01:00",
   "time_added": "2022-09-10T19:29:38+01:00"
  },
  {
   "item_id": "3700230223",
   "given_url": "https://www.quora.com/How-did-Americans-get-the-name-Lee-I-thought-this-is-a-Chinese-name-but-it-s-been-in-America-since-the-Civil-War-Robert-E-Lee-and-I-don-t-think-the-Chinese-have-emigrated-there-yet",
   "given_title": "(15) Question",
   "resolved_title": "How did Americans get the name “Lee”? I thought this is a Chinese name, but it’s been in America since the Civil War (Robert E. Lee), and I don’t think the Chinese have emigrated there yet. - Quora",
   "resolved_url": "https://www.quora.com/How-did-Americans-get-the-name-Lee-I-thought-this-is-a-Chinese-name-but-it-s-been-in-America-since-the-Civil-War-Robert-E-Lee-and-I-don-t-think-the-Chinese-have-emigrated-there-yet",
   "time_updated": "2022-09-10T21:21:30+01:00",
   "time_added": "2022-09-10T21:21:29+01:00"
  },
  {
   "item_id": "3376756761",
   "given_url": "https://vitalflux.com/first-principles-thinking-explained-with-examples/",
   "given_title": "First Principles Thinking: Concepts \u0026 Examples - Data Analytics",
   "resolved_title": "First Principles Thinking: Concepts \u0026 Examples",
   "resolved_url": "https://vitalflux.com/first-principles-thinking-explained-with-examples/",
   "time_updated": "2022-09-10T23:28:41+01:00",
   "time_added": "2022-09-10T23:28:41+01:00"
  },
  {
   "item_id": "3400981369",
   "given_url": "https://dev.to/iggredible/debugging-in-vim-with-vimspector-4n0m",
   "given_title": "Debugging in Vim with Vimspector - DEV Community ?‍??‍?",
   "resolved_title": "Debugging in Vim with Vimspector",
   "resolved_url": "https://dev.to/iggredible/debugging-in-vim-with-vimspector-4n0m",
   "time_updated": "2022-09-11T00:40:49+01:00",
   "time_added": "2022-09-11T00:40:49+01:00"
  },
  {
   "item_id": "3700351213",
   "given_url": "https://twitter.com/dannielduque/status/1568633682872639488",
   "given_title": "Daniel Duque no Twitter: \"Já estive em Buenos Aires duas vezes, e acompanho",
   "resolved_title": "Daniel Duque",
   "resolved_url": "https://twitter.com/dannielduque/status/1568633682872639488",
   "time_updated": "2022-09-11T02:23:16+01:00",
   "time_added": "2022-09-11T02:23:15+01:00"
  },
  {
   "item_id": "3700113193",
   "given_url": "https://beta.reactjs.org/apis/react/useMemo",
   "given_title": "useMemo",
   "resolved_title": "useMemo",
   "resolved_url": "https://beta.reactjs.org/apis/react/useMemo",
   "time_updated": "2022-09-11T15:31:56+01:00",
   "time_added": "2022-09-11T15:31:56+01:00"
  },
  {
   "item_id": "1910120416",
   "given_url": "https://www.poetryfoundation.org/poems/43521/beowulf-old-english-version",
   "given_title": "Beowulf (Old English version) by Anonymous | Poetry Foundation",
   "resolved_title": "Beowulf (Old English version)",
   "resolved_url": "https://www.poetryfoundation.org/poems/43521/beowulf-old-english-version",
   "time_updated": "2022-09-11T16:14:51+01:00",
   "time_added": "2022-09-11T16:14:51+01:00"
  },
  {
   "item_id": "3426130399",
   "given_url": "https://en.wikipedia.org/wiki/Translating_Beowulf",
   "given_title": "Translating Beowulf - Wikipedia",
   "resolved_title": "Translating Beowulf",
   "resolved_url": "https://en.wikipedia.org/wiki/Translating_Beowulf",
   "time_updated": "2022-09-11T16:18:28+01:00",
   "time_added": "2022-09-11T16:18:28+01:00"
  },
  {
   "item_id": "3700708064",
   "given_url": "https://interintellect.com/series/baby-steps-to-beowulf-old-english-for-beginners/",
   "given_title": "Baby Steps to Beowulf: Old English for Beginners - Interintellect",
   "resolved_title": "Baby Steps to Beowulf: Old English for Beginners",
   "resolved_url": "https://interintellect.com/series/baby-steps-to-beowulf-old-english-for-beginners/",
   "time_updated": "2022-09-11T16:18:33+01:00",
   "time_added": "2022-09-11T16:18:30+01:00"
  },
  {
   "item_id": "821244410",
   "given_url": "https://en.wikipedia.org/wiki/On_Translating_Beowulf",
   "given_title": "On Translating Beowulf - Wikipedia",
   "resolved_title": "On Translating Beowulf",
   "resolved_url": "https://en.wikipedia.org/wiki/On_Translating_Beowulf",
   "time_updated": "2022-09-11T16:20:45+01:00",
   "time_added": "2022-09-11T16:20:45+01:00"
  },
  {
   "item_id": "3448440299",
   "given_url": "https://medium.com/@max.p.schlienger/the-cargo-cult-of-the-ennui-engine-890c541cebcb",
   "given_title": "The Cargo Cult of The Ennui Engine | by Max Patrick Schlienger | Medium",
   "resolved_title": "The Cargo Cult of The Ennui Engine",
   "resolved_url": "https://medium.com/@max.p.schlienger/the-cargo-cult-of-the-ennui-engine-890c541cebcb",
   "time_updated": "2022-09-11T21:42:24+01:00",
   "time_added": "2022-09-11T21:42:24+01:00"
  },
  {
   "item_id": "3700898384",
   "given_url": "https://pt.wikipedia.org/wiki/Gandula",
   "given_title": "Gandula – Wikipédia, a enciclopédia livre",
   "resolved_title": "Gandula",
   "resolved_url": "https://pt.wikipedia.org/wiki/Gandula",
   "time_updated": "2022-09-11T22:53:17+01:00",
   "time_added": "2022-09-11T22:53:13+01:00"
  }
 ]
}