{
 "year": "2023",
 "week": "18",
 "sortKey": "2023-18",
 "items": [
  {
   "item_id": "845931525",
   "given_url": "https://www.rogerebert.com/reviews/miracle-mile-1989",
   "given_title": "Miracle Mile movie review \u0026 film summary (1989) | Roger Ebert",
   "resolved_title": "Miracle Mile",
   "resolved_url": "https://www.rogerebert.com/reviews/miracle-mile-1989",
   "time_updated": "2023-05-07T17:11:44Z",
   "time_added": "2023-05-07T17:11:44Z"
  },
  {
   "item_id": "3859041135",
   "given_url": "https://slack.com/blog/news/introducing-slack-gpt",
   "given_title": "Introducing Slack GPT, the future of AI in Slack | Slack",
   "resolved_title": "Introducing Slack GPT, the future of AI in Slack",
   "resolved_url": "https://slack.com/blog/news/introducing-slack-gpt",
   "time_updated": "2023-05-06T21:19:02Z",
   "time_added": "2023-05-06T21:19:01Z"
  },
  {
   "item_id": "3859929198",
   "given_url": "https://zverok.space/blog/2023-05-05-ruby-types.html",
   "given_title": "A few words on Ruby's type annotations state",
   "resolved_title": "A few words on Ruby's type annotations state",
   "resolved_url": "https://zverok.space/blog/2023-05-05-ruby-types.html",
   "time_updated": "2023-05-07T13:25:13Z",
   "time_added": "2023-05-07T13:25:13Z"
  },
  {
   "item_id": "189259672",
   "given_url": "https://en.m.wikipedia.org/wiki/Miracle_Mile_(film)",
   "given_title": "Miracle Mile (film) - Wikipedia",
   "resolved_title": "Miracle Mile (film)",
   "resolved_url": "https://en.wikipedia.org/wiki/Miracle_Mile_(film)",
   "time_updated": "2023-05-07T17:04:33Z",
   "time_added": "2023-05-07T17:04:32Z"
  }
 ]
}