{
 "year": "2023",
 "week": "31",
 "sortKey": "2023-31",
 "items": [
  {
   "item_id": "3913731331",
   "given_url": "https://cienciahoje.org.br/acervo/o-pais-do-novo-homem/",
   "given_title": "O país do ‘novo homem’ | Ciência Hoje",
   "resolved_title": "O país do ‘novo homem’",
   "resolved_url": "https://cienciahoje.org.br/acervo/o-pais-do-novo-homem/",
   "time_updated": "2023-08-03T10:08:24Z",
   "time_added": "2023-08-03T10:08:22Z"
  },
  {
   "item_id": "3914416786",
   "given_url": "https://3010tangents.wordpress.com/2015/03/06/applications-of-imaginary-numbers/",
   "given_title": "Applications of Imaginary Numbers | 3010tangents",
   "resolved_title": "Applications of Imaginary Numbers",
   "resolved_url": "https://3010tangents.wordpress.com/2015/03/06/applications-of-imaginary-numbers/",
   "time_updated": "2023-08-04T15:33:34Z",
   "time_added": "2023-08-04T15:33:33Z"
  },
  {
   "item_id": "3915198808",
   "given_url": "https://filiph.net/text/memex-is-already-here,-it%27s-just-not-evenly-distributed.html",
   "given_title": "Memex is already here, it’s just not evenly distributed",
   "resolved_title": "Memex is already here, it’s just not evenly distributed",
   "resolved_url": "https://filiph.net/text/memex-is-already-here,-it's-just-not-evenly-distributed.html",
   "time_updated": "2023-08-06T12:13:40Z",
   "time_added": "2023-08-06T12:13:39Z"
  },
  {
   "item_id": "3915265528",
   "given_url": "https://pt.m.wikipedia.org/wiki/Terra_preta",
   "given_title": "Terra preta – Wikipédia, a enciclopédia livre",
   "resolved_title": "Terra preta",
   "resolved_url": "https://pt.wikipedia.org/wiki/Terra_preta",
   "time_updated": "2023-08-06T12:17:04Z",
   "time_added": "2023-08-06T12:17:02Z"
  },
  {
   "item_id": "19826324",
   "given_url": "https://en.wikipedia.org/wiki/The_Persistence_of_Memory",
   "given_title": "The Persistence of Memory - Wikipedia",
   "resolved_title": "The Persistence of Memory",
   "resolved_url": "https://en.wikipedia.org/wiki/The_Persistence_of_Memory",
   "time_updated": "2023-08-06T11:58:43Z",
   "time_added": "2023-08-06T11:58:43Z"
  },
  {
   "item_id": "349762905",
   "given_url": "https://en.m.wikipedia.org/wiki/Galago",
   "given_title": "Galago - Wikipedia",
   "resolved_title": "Galago",
   "resolved_url": "https://en.wikipedia.org/wiki/Galago",
   "time_updated": "2023-08-04T21:43:02Z",
   "time_added": "2023-08-04T21:43:01Z"
  },
  {
   "item_id": "3016637200",
   "given_url": "https://www.ligadosgames.com/fusoes-yu-gi-oh-forbidden-memories/",
   "given_title": "Yu-Gi-Oh! Forbidden Memories: veja TODAS as fusões do jogo! - Liga dos Game",
   "resolved_title": "Yu-Gi-Oh! Forbidden Memories: veja TODAS as fusões do jogo!",
   "resolved_url": "https://www.ligadosgames.com/fusoes-yu-gi-oh-forbidden-memories/",
   "time_updated": "2023-08-04T21:49:09Z",
   "time_added": "2023-08-04T21:49:08Z"
  },
  {
   "item_id": "3914914040",
   "given_url": "https://twitter.com/pikuma/status/1687782176828325888",
   "given_title": "pikuma no Twitter: \"Why do we call it the \"Square Root\"? √‾‾‾ We have been ",
   "resolved_title": "",
   "resolved_url": "https://twitter.com/pikuma/status/1687782176828325888",
   "time_updated": "2023-08-05T16:27:39Z",
   "time_added": "2023-08-05T16:27:37Z"
  },
  {
   "item_id": "3266248875",
   "given_url": "https://www.surveymonkey.co.uk/mp/ab-testing-significance-calculator/",
   "given_title": "A/B Testing Calculator for Statistical Significance | SurveyMonkey",
   "resolved_title": "AB testing calculator",
   "resolved_url": "https://www.surveymonkey.co.uk/mp/ab-testing-significance-calculator/",
   "time_updated": "2023-08-05T19:38:34Z",
   "time_added": "2023-08-05T19:38:34Z"
  },
  {
   "item_id": "3915218924",
   "given_url": "https://twitter.com/_JeanLannes/status/1687649736356982784",
   "given_title": "Maréchal Lannes no Twitter: \"Today I learned you can just send JWs to peopl",
   "resolved_title": "",
   "resolved_url": "https://twitter.com/_JeanLannes/status/1687649736356982784",
   "time_updated": "2023-08-06T09:59:26Z",
   "time_added": "2023-08-06T09:59:24Z"
  },
  {
   "item_id": "3912886346",
   "given_url": "https://museumofedible.earth/product/pimba/",
   "given_title": "Pemba Balls Paranam - MUSEUM OF EDIBLE EARTH",
   "resolved_title": "Pemba Balls Paranam",
   "resolved_url": "https://museumofedible.earth/product/pimba/",
   "time_updated": "2023-08-01T20:46:10Z",
   "time_added": "2023-08-01T20:46:08Z"
  },
  {
   "item_id": "3913707431",
   "given_url": "https://m.youtube.com/watch?v=kuQ6pBeJTqg\u0026feature=youtu.be",
   "given_title": "DELETED VID: I got dropped (Roll Dizz Reupload ) - YouTube",
   "resolved_title": "DELETED VID: I got dropped (Roll Dizz Reupload )",
   "resolved_url": "http://www.youtube.com/watch?v=kuQ6pBeJTqg",
   "time_updated": "2023-08-03T09:06:35Z",
   "time_added": "2023-08-03T09:06:33Z"
  },
  {
   "item_id": "1378462419",
   "given_url": "https://viniciusfigueira.com/2011/04/30/vilem-flusser-fenomenologia-do-brasileiro-resenha-rapida-de-uma-leitura-lenta/",
   "given_title": "Vilém Flusser, “Fenomenologia do Brasileiro”: resenha rápida de uma leitura",
   "resolved_title": "Vilém Flusser, “Fenomenologia do Brasileiro”: resenha rápida de uma leitura lenta",
   "resolved_url": "https://viniciusfigueira.com/2011/04/30/vilem-flusser-fenomenologia-do-brasileiro-resenha-rapida-de-uma-leitura-lenta/",
   "time_updated": "2023-08-03T10:13:49Z",
   "time_added": "2023-08-03T10:13:49Z"
  },
  {
   "item_id": "3913885420",
   "given_url": "https://m.facebook.com/story.php/?id=2216008\u0026story_fbid=10105858897519223",
   "given_title": "",
   "resolved_title": "You’re Temporarily Blocked",
   "resolved_url": "https://m.facebook.com/story.php/?id=2216008\u0026story_fbid=10105858897519223",
   "time_updated": "2023-08-03T15:54:48Z",
   "time_added": "2023-08-03T15:54:46Z"
  },
  {
   "item_id": "3914111272",
   "given_url": "https://www.uol.com.br/carros/reportagens-especiais/sexo-no-carro/#page7",
   "given_title": "Tesão sobre rodas: relação entre sexo e carros tem voyerismo e poder",
   "resolved_title": "Tesão sobre rodas",
   "resolved_url": "https://www.uol.com.br/carros/reportagens-especiais/sexo-no-carro/",
   "time_updated": "2023-08-04T03:56:57Z",
   "time_added": "2023-08-04T03:56:57Z"
  },
  {
   "item_id": "3914821962",
   "given_url": "https://twitter.com/techsavvytravvy/status/1687320153095098368/photo/1",
   "given_title": "trav no Twitter: \"skill issue tbh https://t.co/VlSL7mrnHV\" / X",
   "resolved_title": "",
   "resolved_url": "https://twitter.com/techsavvytravvy/status/1687320153095098368/photo/1",
   "time_updated": "2023-08-05T12:24:37Z",
   "time_added": "2023-08-05T12:24:36Z"
  },
  {
   "item_id": "103226000",
   "given_url": "https://en.m.wikipedia.org/wiki/Maroons",
   "given_title": "Maroons - Wikipedia",
   "resolved_title": "Maroons",
   "resolved_url": "https://en.wikipedia.org/wiki/Maroons",
   "time_updated": "2023-08-03T23:26:09Z",
   "time_added": "2023-08-03T23:26:08Z"
  },
  {
   "item_id": "3914591819",
   "given_url": "https://www1.folha.uol.com.br/colunas/demetriomagnoli/2023/08/a-palavra-blasfema.shtml",
   "given_title": "A palavra blasfema - 04/08/2023 - Demétrio Magnoli - Folha",
   "resolved_title": "A palavra blasfema",
   "resolved_url": "https://www1.folha.uol.com.br/colunas/demetriomagnoli/2023/08/a-palavra-blasfema.shtml",
   "time_updated": "2023-08-05T16:40:45Z",
   "time_added": "2023-08-05T16:40:44Z"
  },
  {
   "item_id": "3665128556",
   "given_url": "https://noticias.uol.com.br/internacional/ultimas-noticias/2022/07/21/por-que-calor-de-40c-causa-panico-na-inglaterra-e-no-brasil-e-normal.htm",
   "given_title": "Onde de calor na Europa: por que 40ªC lá é pior que Brasil?",
   "resolved_title": "Por que calor de 40ºC é mortal na Inglaterra e no Brasil é \"normal\"?",
   "resolved_url": "https://noticias.uol.com.br/internacional/ultimas-noticias/2022/07/21/por-que-calor-de-40c-causa-panico-na-inglaterra-e-no-brasil-e-normal.htm",
   "time_updated": "2023-08-06T12:42:13Z",
   "time_added": "2023-08-06T12:42:13Z"
  },
  {
   "item_id": "805481389",
   "given_url": "https://pt.m.wikipedia.org/wiki/%C3%87atalh%C3%BCy%C3%BCk",
   "given_title": "Çatalhüyük – Wikipédia, a enciclopédia livre",
   "resolved_title": "Çatalhüyük",
   "resolved_url": "https://pt.wikipedia.org/wiki/%C3%87atalh%C3%BCy%C3%BCk",
   "time_updated": "2023-08-06T12:17:18Z",
   "time_added": "2023-08-06T12:17:18Z"
  },
  {
   "item_id": "3914348707",
   "given_url": "https://sampi.net.br/bauru/noticias/2235392/tribuna_do_leitor/2016/12/origem-das-expressoes",
   "given_title": "Origem das expressões",
   "resolved_title": "Origem das expressões",
   "resolved_url": "https://sampi.net.br/bauru/noticias/2235392/tribuna_do_leitor/2016/12/origem-das-expressoes",
   "time_updated": "2023-08-04T13:05:03Z",
   "time_added": "2023-08-04T13:05:01Z"
  },
  {
   "item_id": "1035680416",
   "given_url": "https://pt.m.wikipedia.org/wiki/Sedevacantismo",
   "given_title": "Sedevacantismo – Wikipédia, a enciclopédia livre",
   "resolved_title": "Sedevacantismo",
   "resolved_url": "https://pt.wikipedia.org/wiki/Sedevacantismo",
   "time_updated": "2023-08-05T09:29:04Z",
   "time_added": "2023-08-05T09:29:03Z"
  },
  {
   "item_id": "3897235361",
   "given_url": "https://en.m.wikipedia.org/wiki/Hwang_affair",
   "given_title": "Hwang affair - Wikipedia",
   "resolved_title": "Hwang affair",
   "resolved_url": "https://en.wikipedia.org/wiki/Hwang_affair",
   "time_updated": "2023-08-05T09:43:06Z",
   "time_added": "2023-08-05T09:43:05Z"
  },
  {
   "item_id": "3914787497",
   "given_url": "https://twitter.com/SebAaltonen/status/1687691543157829632",
   "given_title": "Sebastian Aaltonen @ SIGGRAPH no Twitter: \"A thread about rollback network ",
   "resolved_title": "",
   "resolved_url": "https://twitter.com/SebAaltonen/status/1687691543157829632",
   "time_updated": "2023-08-05T12:51:09Z",
   "time_added": "2023-08-05T12:51:09Z"
  },
  {
   "item_id": "3915008364",
   "given_url": "https://twitter.com/mattpocockuk/status/1687906780800487424",
   "given_title": "Matt Pocock no Twitter: \"I'm starting to get interested in AI. Specifically",
   "resolved_title": "",
   "resolved_url": "https://twitter.com/mattpocockuk/status/1687906780800487424",
   "time_updated": "2023-08-05T21:19:23Z",
   "time_added": "2023-08-05T21:19:21Z"
  },
  {
   "item_id": "3912404819",
   "given_url": "https://twitter.com/akita_kt/status/1686151926088392705",
   "given_title": "shi?️a | shibashiboso.bsky.social no Twitter: \"Errado: Yasuke não era um sa",
   "resolved_title": "",
   "resolved_url": "https://twitter.com/akita_kt/status/1686151926088392705",
   "time_updated": "2023-08-01T17:17:02Z",
   "time_added": "2023-08-01T17:17:02Z"
  },
  {
   "item_id": "277357183",
   "given_url": "https://en.m.wikipedia.org/wiki/Jean_Berko_Gleason",
   "given_title": "Jean Berko Gleason - Wikipedia",
   "resolved_title": "Jean Berko Gleason",
   "resolved_url": "http://en.m.wikipedia.org/wiki/Jean_Berko_Gleason",
   "time_updated": "2023-08-02T20:53:22Z",
   "time_added": "2023-08-02T20:53:22Z"
  },
  {
   "item_id": "1196140255",
   "given_url": "https://hbr.org/2016/02/a-refresher-on-statistical-significance",
   "given_title": "A Refresher on Statistical Significance",
   "resolved_title": "A Refresher on Statistical Significance",
   "resolved_url": "https://hbr.org/2016/02/a-refresher-on-statistical-significance",
   "time_updated": "2023-08-05T19:54:34Z",
   "time_added": "2023-08-05T19:54:34Z"
  },
  {
   "item_id": "3915056433",
   "given_url": "https://twitter.com/agsportlight/status/1687963462830284800",
   "given_title": "Agência Sportlight no Twitter: \"Falcão está nas manchetes por grave denúnci",
   "resolved_title": "",
   "resolved_url": "https://twitter.com/agsportlight/status/1687963462830284800",
   "time_updated": "2023-08-06T00:17:29Z",
   "time_added": "2023-08-06T00:17:27Z"
  }
 ]
}