{
 "year": "2023",
 "week": "21",
 "sortKey": "2023-21",
 "items": [
  {
   "item_id": "3869065056",
   "given_url": "http://thesiskoday.com/",
   "given_title": "The Sisko Day",
   "resolved_title": "THE SISKO DAY SCHEDULE | 5.22.23",
   "resolved_url": "http://thesiskoday.com/",
   "time_updated": "2023-05-22T12:34:45Z",
   "time_added": "2023-05-22T12:34:44Z"
  },
  {
   "item_id": "3871431811",
   "given_url": "https://twitter.com/UnseenJapanSite/status/1661052179711692800?t=gKqtjKqYANfCziC8g9KXHw\u0026s=19",
   "given_title": "(2) Unseen Japan no Twitter: \"Kimura Kyoko, mother of deceased pro wrestler",
   "resolved_title": "",
   "resolved_url": "https://twitter.com/UnseenJapanSite/status/1661052179711692800?t=gKqtjKqYANfCziC8g9KXHw\u0026s=19",
   "time_updated": "2023-05-23T18:01:21Z",
   "time_added": "2023-05-23T18:01:20Z"
  },
  {
   "item_id": "3863009071",
   "given_url": "https://samwho.dev/memory-allocation/",
   "given_title": "Memory Allocation",
   "resolved_title": "Memory Allocation",
   "resolved_url": "https://samwho.dev/memory-allocation/",
   "time_updated": "2023-05-22T14:28:59Z",
   "time_added": "2023-05-22T14:28:59Z"
  },
  {
   "item_id": "3763581445",
   "given_url": "https://knowyourmeme.com/memes/mario-the-idea-vs-mario-the-man",
   "given_title": "Mario, the Idea vs. Mario, the Man | Know Your Meme",
   "resolved_title": "",
   "resolved_url": "https://knowyourmeme.com/memes/mario-the-idea-vs-mario-the-man",
   "time_updated": "2023-05-22T14:09:42Z",
   "time_added": "2023-05-22T14:09:41Z"
  },
  {
   "item_id": "3870544229",
   "given_url": "https://www.uol.com.br/esporte/colunas/milton-neves/2023/05/22/luto-morre-o-treinador-vagner-benazzi-o-rei-do-acesso.htm",
   "given_title": "Luto! Morre o treinador Vágner Benazzi, o 'Rei do Acesso' - 22/05/2023 - UO",
   "resolved_title": "Luto! Morre o treinador Vágner Benazzi, o 'Rei do Acesso'",
   "resolved_url": "https://www.uol.com.br/esporte/colunas/milton-neves/2023/05/22/luto-morre-o-treinador-vagner-benazzi-o-rei-do-acesso.htm",
   "time_updated": "2023-05-22T18:35:13Z",
   "time_added": "2023-05-22T18:35:12Z"
  },
  {
   "item_id": "3870769597",
   "given_url": "https://www1.folha.uol.com.br/esporte/2023/05/caso-de-vinicius-junior-divide-a-espanha-e-enfrenta-ideia-de-que-racismo-e-injustificavel-mas.shtml",
   "given_title": "Caso de Vinicius Junior divide a Espanha - 22/05/2023 - Esporte - Folha",
   "resolved_title": "Caso de Vinicius Junior divide a Espanha e enfrenta ideia de que racismo é 'injustificável, mas...'",
   "resolved_url": "https://www1.folha.uol.com.br/esporte/2023/05/caso-de-vinicius-junior-divide-a-espanha-e-enfrenta-ideia-de-que-racismo-e-injustificavel-mas.shtml",
   "time_updated": "2023-05-22T23:11:53Z",
   "time_added": "2023-05-22T23:11:52Z"
  },
  {
   "item_id": "2462894597",
   "given_url": "https://ciechanow.ski/archives/",
   "given_title": "Archives - Bartosz Ciechanowski",
   "resolved_title": "Archives",
   "resolved_url": "https://ciechanow.ski/archives/",
   "time_updated": "2023-05-22T14:39:35Z",
   "time_added": "2023-05-22T14:39:35Z"
  },
  {
   "item_id": "3869026110",
   "given_url": "https://riskmusings.substack.com/p/success-to-the-successful",
   "given_title": "Success to the Successful - by Stephanie Losi",
   "resolved_title": "Success to the Successful",
   "resolved_url": "https://riskmusings.substack.com/p/success-to-the-successful",
   "time_updated": "2023-05-23T11:29:22Z",
   "time_added": "2023-05-23T11:29:22Z"
  },
  {
   "item_id": "3870480638",
   "given_url": "https://www.youtube.com/watch?v=XxgjGJeg820",
   "given_title": "(65) How to Use 悪い - YouTube",
   "resolved_title": "How to Use 悪い",
   "resolved_url": "https://www.youtube.com/watch?v=XxgjGJeg820",
   "time_updated": "2023-05-22T11:44:06Z",
   "time_added": "2023-05-22T11:44:05Z"
  },
  {
   "item_id": "3870625239",
   "given_url": "https://stackoverflow.blog/2023/05/22/modern-work-requires-attention-constant-alerts-steal-it/",
   "given_title": "Modern work requires attention. Constant alerts steal it - Stack Overflow B",
   "resolved_title": "Modern work requires attention. Constant alerts steal it",
   "resolved_url": "https://stackoverflow.blog/2023/05/22/modern-work-requires-attention-constant-alerts-steal-it/",
   "time_updated": "2023-05-23T11:21:05Z",
   "time_added": "2023-05-23T11:21:04Z"
  }
 ]
}