{
 "year": "2023",
 "week": "46",
 "sortKey": "2023-46",
 "items": [
  {
   "item_id": "3071606237",
   "given_url": "https://mixedname.com/",
   "given_title": "Bilingual baby name finder",
   "resolved_title": "Find bilingual baby names",
   "resolved_url": "https://mixedname.com/",
   "time_updated": "2023-11-13T00:30:54Z",
   "time_added": "2023-11-13T00:30:54Z"
  },
  {
   "item_id": "679948126",
   "given_url": "https://en.m.wikipedia.org/wiki/Glossary_of_jive_talk",
   "given_title": "Glossary of jive talk - Wikipedia",
   "resolved_title": "Glossary of jive talk",
   "resolved_url": "https://en.wikipedia.org/wiki/Glossary_of_jive_talk",
   "time_updated": "2023-11-13T18:05:44Z",
   "time_added": "2023-11-13T18:05:43Z"
  }
 ]
}