{
 "year": "2024",
 "week": "31",
 "sortKey": "2024-31",
 "items": [
  {
   "item_id": "80714753",
   "given_url": "https://en.m.wikipedia.org/wiki/Barnum_effect",
   "given_title": "Barnum effect - Wikipedia",
   "resolved_title": "Barnum effect",
   "resolved_url": "https://en.wikipedia.org/wiki/Barnum_effect",
   "time_updated": "2024-08-02T08:17:32Z",
   "time_added": "2024-08-02T08:17:31Z"
  },
  {
   "item_id": "4084056148",
   "given_url": "https://pt.m.wikipedia.org/wiki/Pernilongo",
   "given_title": "Pernilongo – Wikipédia, a enciclopédia livre",
   "resolved_title": "Pernilongo",
   "resolved_url": "https://pt.wikipedia.org/wiki/Pernilongo",
   "time_updated": "2024-08-02T08:55:33Z",
   "time_added": "2024-08-02T08:55:30Z"
  },
  {
   "item_id": "4084140855",
   "given_url": "https://dotesports.com/streaming/news/zombie-brand-amazon-reportedly-losing-hope-in-1-billion-buy-twitch-as-profits-slump",
   "given_title": "'Zombie brand': Amazon reportedly losing hope in $1 billion buy Twitch as p",
   "resolved_title": "‘Zombie brand’: Amazon reportedly losing hope in $1 billion buy Twitch as profits slump",
   "resolved_url": "https://dotesports.com/streaming/news/zombie-brand-amazon-reportedly-losing-hope-in-1-billion-buy-twitch-as-profits-slump",
   "time_updated": "2024-08-02T13:16:06Z",
   "time_added": "2024-08-02T13:16:04Z"
  },
  {
   "item_id": "4084173931",
   "given_url": "https://www.youtube.com/watch?v=tBpnKTAc5Eo\u0026list=PLjEaoINr3zgEPv5y--4MKpciLaoQYZB1Z\u0026index=2",
   "given_title": "Beginner Blender 4.0 Tutorial - Part 2: Basic Modelling - YouTube",
   "resolved_title": "Beginner Blender 4.0 Tutorial - Part 2: Basic Modelling",
   "resolved_url": "https://www.youtube.com/watch?v=tBpnKTAc5Eo\u0026list=PLjEaoINr3zgEPv5y--4MKpciLaoQYZB1Z\u0026index=2",
   "time_updated": "2024-08-02T14:50:27Z",
   "time_added": "2024-08-02T14:50:26Z"
  },
  {
   "item_id": "4084222009",
   "given_url": "http://www.cozinhaousada.com/2013/03/coracao-de-bananeira.html?m=1",
   "given_title": "Cozinha Ousada: Coração de Bananeira",
   "resolved_title": "Coração de Bananeira",
   "resolved_url": "http://www.cozinhaousada.com/2013/03/coracao-de-bananeira.html",
   "time_updated": "2024-08-02T17:00:50Z",
   "time_added": "2024-08-02T17:00:47Z"
  },
  {
   "item_id": "3353225713",
   "given_url": "https://viagens.sapo.pt/viajar/viajar-portugal/artigos/salinas-do-samouco-um-santuario-de-natureza-as-portas-de-lisboa",
   "given_title": "Salinas do Samouco: um santuário de natureza às portas de Lisboa - Portugal",
   "resolved_title": "Salinas do Samouco: um santuário de natureza às portas de Lisboa",
   "resolved_url": "https://viagens.sapo.pt/viajar/viajar-portugal/artigos/salinas-do-samouco-um-santuario-de-natureza-as-portas-de-lisboa",
   "time_updated": "2024-08-02T17:30:17Z",
   "time_added": "2024-08-02T17:30:16Z"
  },
  {
   "item_id": "4084264706",
   "given_url": "https://m.youtube.com/watch?v=e2jx7hWJMEA",
   "given_title": "Top Ten Fencers in Fighting Games - YouTube",
   "resolved_title": "Top Ten Fencers in Fighting Games",
   "resolved_url": "http://www.youtube.com/watch?v=e2jx7hWJMEA",
   "time_updated": "2024-08-02T19:21:11Z",
   "time_added": "2024-08-02T19:21:07Z"
  },
  {
   "item_id": "4084335498",
   "given_url": "https://m.youtube.com/watch?v=9eAkr6Lhhsw",
   "given_title": "The Dominion War Chronicles - YouTube",
   "resolved_title": "The Dominion War Chronicles",
   "resolved_url": "http://www.youtube.com/watch?v=9eAkr6Lhhsw",
   "time_updated": "2024-08-02T23:40:34Z",
   "time_added": "2024-08-02T23:40:30Z"
  },
  {
   "item_id": "565276849",
   "given_url": "https://pt.m.wikipedia.org/wiki/Futev%C3%B4lei",
   "given_title": "Futevôlei – Wikipédia, a enciclopédia livre",
   "resolved_title": "Futevôlei",
   "resolved_url": "http://pt.m.wikipedia.org/wiki/Futev%C3%B4lei",
   "time_updated": "2024-08-03T08:28:52Z",
   "time_added": "2024-08-03T08:28:51Z"
  },
  {
   "item_id": "4084202339",
   "given_url": "https://news.ycombinator.com/item?id=41139149",
   "given_title": "The upstream cause of the youth mental health crisis is the loss of communi",
   "resolved_title": "The Upstream Cause of the Youth Mental Health Crisis Is the Loss of Community",
   "resolved_url": "https://news.ycombinator.com/item?id=41139149",
   "time_updated": "2024-08-03T19:49:22Z",
   "time_added": "2024-08-03T19:49:19Z"
  },
  {
   "item_id": "4084683753",
   "given_url": "https://m.youtube.com/watch?v=N7GsLni7Ybo",
   "given_title": "Sega RPGs I Wish I Played - YouTube",
   "resolved_title": "Sega RPGs I Wish I Played",
   "resolved_url": "http://www.youtube.com/watch?v=N7GsLni7Ybo",
   "time_updated": "2024-08-03T21:48:26Z",
   "time_added": "2024-08-03T21:48:22Z"
  },
  {
   "item_id": "4085011629",
   "given_url": "https://www.worldarchery.sport/news/178452/archery-history-legend-robin-hood",
   "given_title": "Archery history: The legend of Robin Hood | World Archery",
   "resolved_title": "Archery history: The legend of Robin Hood",
   "resolved_url": "https://www.worldarchery.sport/news/178452/archery-history-legend-robin-hood",
   "time_updated": "2024-08-04T18:32:48Z",
   "time_added": "2024-08-04T18:32:45Z"
  }
 ]
}