{
 "year": "2024",
 "week": "49",
 "sortKey": "2024-49",
 "items": [
  {
   "item_id": "4145679648",
   "given_url": "https://docs.google.com/document/u/0/d/1JSH_CVIz2yysWp4PKIrmB3nwUf6d9rzlMuYsiVs7UE4/mobilebasic",
   "given_title": "A Gringa's Great Greasy Guide to Brasil",
   "resolved_title": "Table of contents",
   "resolved_url": "https://docs.google.com/document/u/0/d/1JSH_CVIz2yysWp4PKIrmB3nwUf6d9rzlMuYsiVs7UE4/mobilebasic",
   "time_updated": "2024-12-07T15:42:03Z",
   "time_added": "2024-12-07T15:41:47Z"
  },
  {
   "item_id": "4146151934",
   "given_url": "https://site.videobrasil.org.br/acervo/obras/obra/392456",
   "given_title": "TV Livre, Sorocaba - Videobrasil",
   "resolved_title": "TV Livre, Sorocaba",
   "resolved_url": "https://site.videobrasil.org.br/acervo/obras/obra/392456",
   "time_updated": "2024-12-08T17:16:57Z",
   "time_added": "2024-12-08T17:16:55Z"
  },
  {
   "item_id": "4128517152",
   "given_url": "https://www.justinmath.com/the-necessity-of-grinding-through-concrete-examples-before-jumping-up-a-level-of-abstraction/",
   "given_title": "The Necessity of Grinding Through Concrete Examples Before Jumping Up a Lev",
   "resolved_title": "The Necessity of Grinding Through Concrete Examples Before Jumping Up a Level of Abstraction",
   "resolved_url": "https://justinmath.com/the-necessity-of-grinding-through-concrete-examples-before-jumping-up-a-level-of-abstraction/",
   "time_updated": "2024-12-08T19:14:18Z",
   "time_added": "2024-12-08T19:14:17Z"
  }
 ]
}