{
 "year": "2024",
 "week": "52",
 "sortKey": "2024-52",
 "items": [
  {
   "item_id": "4154068656",
   "given_url": "https://m.youtube.com/watch?v=FdKjvtdwuvM\u0026t=40s\u0026pp=2AEokAIB",
   "given_title": "Tomb Raider Remastered - Colosseum 3rd Secret, Modern vs. Tank controls dem",
   "resolved_title": "Tomb Raider Remastered - Colosseum 3rd Secret, Modern vs. Tank controls demonstration",
   "resolved_url": "http://www.youtube.com/watch?v=FdKjvtdwuvM",
   "time_updated": "2024-12-24T20:04:12Z",
   "time_added": "2024-12-24T20:04:09Z"
  },
  {
   "item_id": "4154202382",
   "given_url": "https://www.reddit.com/r/brasil/s/uXA8Fjgu5x",
   "given_title": "",
   "resolved_title": "É o melhor Natal desde 2013, mas não parece",
   "resolved_url": "https://www.reddit.com/r/brasil/comments/1hlngcx/comment/m3ny91z?share_id=0erjyz4JXAxwpo0too-DY\u0026utm_content=2\u0026utm_medium=android_app\u0026utm_name=androidcss\u0026utm_source=share\u0026utm_term=2",
   "time_updated": "2024-12-25T05:34:53Z",
   "time_added": "2024-12-25T05:34:50Z"
  },
  {
   "item_id": "4154297101",
   "given_url": "https://www.reddit.com/r/TombRaider/comments/1dp2o8x/just_completed_tomb_raider_remastered_thoughts/",
   "given_title": "Just completed Tomb Raider Remastered - Thoughts : r/TombRaider",
   "resolved_title": "Just completed Tomb Raider Remastered - Thoughts",
   "resolved_url": "https://www.reddit.com/r/TombRaider/comments/1dp2o8x/just_completed_tomb_raider_remastered_thoughts/",
   "time_updated": "2024-12-25T12:35:20Z",
   "time_added": "2024-12-25T12:35:18Z"
  },
  {
   "item_id": "4154311565",
   "given_url": "https://boundingintocomics.com/video-games/despite-promise-games-would-appear-in-their-original-form-tomb-raider-i-iii-remastered-censors-risque-graphic-found-on-pierres-jacket/",
   "given_title": "Despite Promise Games Would Appear In Their \"Original Form\", 'Tomb Raider I",
   "resolved_title": "Despite Promise Games Would Appear In Their “Original Form”, ‘Tomb Raider I-III Remastered’ Censors Risqué Graphic Found On Pierre’s Jacket",
   "resolved_url": "https://boundingintocomics.com/video-games/despite-promise-games-would-appear-in-their-original-form-tomb-raider-i-iii-remastered-censors-risque-graphic-found-on-pierres-jacket/",
   "time_updated": "2024-12-25T13:26:55Z",
   "time_added": "2024-12-25T13:26:53Z"
  },
  {
   "item_id": "4154363677",
   "given_url": "https://pt.m.wikipedia.org/wiki/Jararaca-da-mata",
   "given_title": "Jararaca-da-mata – Wikipédia, a enciclopédia livre",
   "resolved_title": "Jararaca-da-mata",
   "resolved_url": "https://pt.wikipedia.org/wiki/Jararaca-da-mata",
   "time_updated": "2024-12-25T16:31:36Z",
   "time_added": "2024-12-25T16:31:33Z"
  },
  {
   "item_id": "4119194576",
   "given_url": "https://minds.md/zakirullin/cognitive",
   "given_title": "Cognitive load is what matters",
   "resolved_title": "Cognitive load",
   "resolved_url": "https://minds.md/zakirullin/cognitive",
   "time_updated": "2024-12-25T18:33:31Z",
   "time_added": "2024-12-25T18:33:28Z"
  },
  {
   "item_id": "4148222925",
   "given_url": "https://hothardware.com/news/heinekens-game-controller-will-let-you-know-when-its-time-for-a-drink",
   "given_title": "Heineken's Game Controller Will Let You Know When It's Time For A Drink | H",
   "resolved_title": "Heineken's Game Controller Will Let You Know When It's Time For A Drink",
   "resolved_url": "https://hothardware.com/news/heinekens-game-controller-will-let-you-know-when-its-time-for-a-drink",
   "time_updated": "2024-12-26T00:39:21Z",
   "time_added": "2024-12-26T00:39:16Z"
  },
  {
   "item_id": "210102717",
   "given_url": "https://en.m.wikipedia.org/wiki/Metal_Gear_Acid_2",
   "given_title": "Metal Gear Acid 2 - Wikipedia",
   "resolved_title": "Metal Gear Acid 2",
   "resolved_url": "https://en.wikipedia.org/wiki/Metal_Gear_Acid_2",
   "time_updated": "2024-12-26T00:53:28Z",
   "time_added": "2024-12-26T00:53:27Z"
  }
 ]
}