{
 "year": "2024",
 "week": "11",
 "sortKey": "2024-11",
 "items": [
  {
   "item_id": "4021119319",
   "given_url": "https://www.uol.com.br/tilt/colunas/blog-do-dunker/2024/03/12/bancas-de-heteroidentificacao-quando-leis-para-incluir-acabam-ferindo.htm",
   "given_title": "Bancas de heteroidentificação: quando leis para incluir acabam ferindo",
   "resolved_title": "Bancas de heteroidentificação: quando leis para incluir acabam ferindo",
   "resolved_url": "https://www.uol.com.br/tilt/colunas/blog-do-dunker/2024/03/12/bancas-de-heteroidentificacao-quando-leis-para-incluir-acabam-ferindo.htm",
   "time_updated": "2024-03-12T18:07:13Z",
   "time_added": "2024-03-12T18:07:13Z"
  },
  {
   "item_id": "1007024071",
   "given_url": "https://en.m.wikipedia.org/wiki/Izmail",
   "given_title": "Izmail - Wikipedia",
   "resolved_title": "Izmail",
   "resolved_url": "https://en.wikipedia.org/wiki/Izmail",
   "time_updated": "2024-03-12T13:25:10Z",
   "time_added": "2024-03-12T13:25:09Z"
  },
  {
   "item_id": "115064258",
   "given_url": "https://en.m.wikipedia.org/wiki/Alice_in_Wonderland_syndrome",
   "given_title": "Alice in Wonderland syndrome - Wikipedia",
   "resolved_title": "Alice in Wonderland syndrome",
   "resolved_url": "https://en.wikipedia.org/wiki/Alice_in_Wonderland_syndrome",
   "time_updated": "2024-03-12T20:00:10Z",
   "time_added": "2024-03-12T20:00:09Z"
  },
  {
   "item_id": "1305598999",
   "given_url": "https://en.m.wikipedia.org/wiki/Bez_(dancer)",
   "given_title": "Bez (dancer) - Wikipedia",
   "resolved_title": "Bez (dancer)",
   "resolved_url": "https://en.wikipedia.org/wiki/Bez_(dancer)",
   "time_updated": "2024-03-11T20:24:13Z",
   "time_added": "2024-03-11T20:24:09Z"
  }
 ]
}